limalight/__init__.py
limalight/base_display.py
limalight/cli.py
limalight/display_factory.py
limalight/main.py
limalight/oled_display.py
limalight/terminal_display.py
limalight-0.1.3.dist-info/METADATA
limalight-0.1.3.dist-info/WHEEL
limalight-0.1.3.dist-info/entry_points.txt
limalight-0.1.3.dist-info/RECORD
